odoo/addons/hr_expense_tax_adjust/README.rst
odoo/addons/hr_expense_tax_adjust/__init__.py
odoo/addons/hr_expense_tax_adjust/__manifest__.py
odoo/addons/hr_expense_tax_adjust/i18n/hr_expense_tax_adjust.pot
odoo/addons/hr_expense_tax_adjust/i18n/it.po
odoo/addons/hr_expense_tax_adjust/models/__init__.py
odoo/addons/hr_expense_tax_adjust/models/hr_expense.py
odoo/addons/hr_expense_tax_adjust/readme/CONTRIBUTORS.rst
odoo/addons/hr_expense_tax_adjust/readme/DESCRIPTION.rst
odoo/addons/hr_expense_tax_adjust/readme/USAGE.rst
odoo/addons/hr_expense_tax_adjust/static/description/icon.png
odoo/addons/hr_expense_tax_adjust/static/description/index.html
odoo/addons/hr_expense_tax_adjust/tests/__init__.py
odoo/addons/hr_expense_tax_adjust/tests/test_hr_expense_tax_adjust.py
odoo/addons/hr_expense_tax_adjust/views/hr_expense_views.xml
odoo_addon_hr_expense_tax_adjust-15.0.1.1.1.dist-info/METADATA
odoo_addon_hr_expense_tax_adjust-15.0.1.1.1.dist-info/WHEEL
odoo_addon_hr_expense_tax_adjust-15.0.1.1.1.dist-info/top_level.txt
odoo_addon_hr_expense_tax_adjust-15.0.1.1.1.dist-info/RECORD
